aangaraa_pay/__init__.py
aangaraa_pay/payment.py
zaz_aangaraa_pay_python-0.1.0.dist-info/LICENSE
zaz_aangaraa_pay_python-0.1.0.dist-info/METADATA
zaz_aangaraa_pay_python-0.1.0.dist-info/WHEEL
zaz_aangaraa_pay_python-0.1.0.dist-info/top_level.txt
zaz_aangaraa_pay_python-0.1.0.dist-info/RECORD
