Metadata-Version: 2.1
Name: zaz-aangaraa-pay-python
Version: 0.1.0
Summary: A Python package for integrating MTN and Orange Money payments in Cameroon
Home-page: https://github.com/Achaire-Zogo/aangaraa_pay_python
Author: Achaire Zogo
Author-email: dylanabouma@gmail.com
Classifier: Programming Language :: Python :: 3
Classifier: License :: OSI Approved :: MIT License
Classifier: Operating System :: OS Independent
Requires-Python: >=3.6
License-File: LICENSE
Requires-Dist: requests
